cirq_aqt/__init__.py
cirq_aqt/_version.py
cirq_aqt/_version_test.py
cirq_aqt/aqt_device.py
cirq_aqt/aqt_device_metadata.py
cirq_aqt/aqt_device_metadata_test.py
cirq_aqt/aqt_device_test.py
cirq_aqt/aqt_sampler.py
cirq_aqt/aqt_sampler_test.py
cirq_aqt/aqt_simulator_test.py
cirq_aqt/aqt_target_gateset.py
cirq_aqt/aqt_target_gateset_test.py
cirq_aqt/conftest.py
cirq_aqt/json_resolver_cache.py
cirq_aqt/json_test_data/__init__.py
cirq_aqt/json_test_data/spec.py
cirq_aqt-1.6.0.dist-info/licenses/LICENSE
cirq_aqt-1.6.0.dist-info/METADATA
cirq_aqt-1.6.0.dist-info/WHEEL
cirq_aqt-1.6.0.dist-info/top_level.txt
cirq_aqt-1.6.0.dist-info/RECORD
