Metadata-Version: 2.4
Name: cirq-aqt
Version: 1.6.0
Summary: A Cirq package to simulate and connect to Alpine Quantum Technologies quantum computers
Home-page: http://github.com/quantumlib/cirq
Author: The Cirq Developers
Author-email: cirq-dev@googlegroups.com
Maintainer: Google Quantum AI open-source maintainers
Maintainer-email: quantum-oss-maintainers@google.com
License: Apache 2
Keywords: algorithms,api,cirq,google,google quantum,nisq,python,quantum,quantum algorithms,quantum circuit,quantum circuit simulator,quantum computer simulator,quantum computing,quantum development kit,quantum information,quantum programming,quantum programming language,quantum simulation,sdk,simulation
Classifier: Development Status :: 5 - Production/Stable
Classifier: Intended Audience :: Developers
Classifier: Intended Audience :: Education
Classifier: Intended Audience :: Science/Research
Classifier: License :: OSI Approved :: Apache Software License
Classifier: Operating System :: MacOS :: MacOS X
Classifier: Operating System :: Microsoft :: Windows
Classifier: Operating System :: POSIX :: Linux
Classifier: Programming Language :: Python :: 3
Classifier: Programming Language :: Python :: 3.11
Classifier: Programming Language :: Python :: 3.12
Classifier: Programming Language :: Python :: 3.13
Classifier: Topic :: Scientific/Engineering :: Quantum Computing
Classifier: Topic :: Software Development :: Libraries :: Python Modules
Classifier: Typing :: Typed
Requires-Python: >=3.11.0
License-File: LICENSE
Requires-Dist: requests~=2.32
Requires-Dist: cirq-core==1.6.0
Dynamic: author
Dynamic: author-email
Dynamic: classifier
Dynamic: description
Dynamic: description-content-type
Dynamic: home-page
Dynamic: keywords
Dynamic: license
Dynamic: license-file
Dynamic: maintainer
Dynamic: maintainer-email
Dynamic: requires-dist
Dynamic: requires-python
Dynamic: summary
